flask_profiler/__init__.py
flask_profiler/flask_profiler.py
flask_profiler/static/dist/index.html
flask_profiler/static/dist/login.html
flask_profiler/static/dist/version.txt
flask_profiler/static/dist/css/jquery.json-viewer.css
flask_profiler/static/dist/css/main.css
flask_profiler/static/dist/fonts/glyphicons-halflings-regular.eot
flask_profiler/static/dist/fonts/glyphicons-halflings-regular.svg
flask_profiler/static/dist/fonts/glyphicons-halflings-regular.ttf
flask_profiler/static/dist/fonts/glyphicons-halflings-regular.woff
flask_profiler/static/dist/images/python-flask.png
flask_profiler/static/dist/js/jquery.json-viewer.js
flask_profiler/static/dist/js/main.js
flask_profiler/static/dist/js/main2.js
flask_profiler/storage/__init__.py
flask_profiler/storage/base.py
flask_profiler/storage/mongo.py
flask_profiler/storage/sql_alchemy.py
flask_profiler/storage/sqlite.py
Flask_ProfilerForked-1.8.5.dist-info/LICENSE
Flask_ProfilerForked-1.8.5.dist-info/METADATA
Flask_ProfilerForked-1.8.5.dist-info/WHEEL
Flask_ProfilerForked-1.8.5.dist-info/top_level.txt
Flask_ProfilerForked-1.8.5.dist-info/RECORD
