Metadata-Version: 2.2
Name: Flask-ProfilerForked
Version: 1.8.5
Summary: API endpoint profiler for Flask framework
Home-page: https://github.com/Kalmai221/FlaskProfilerForked
Author: Kalmai221
Author-email: Kalmai221PlaysOfficial@gmail.com
License: The MIT License (MIT)
Keywords: profiler,flask,performance,optimization
Platform: any
Classifier: Environment :: Web Environment
Classifier: Intended Audience :: Developers
Classifier: License :: OSI Approved :: MIT License
Classifier: Operating System :: OS Independent
Classifier: Programming Language :: Python
Classifier: Programming Language :: Python :: 3
Classifier: Topic :: Internet :: WWW/HTTP :: Dynamic Content
Classifier: Topic :: Software Development :: Libraries :: Python Modules
License-File: LICENSE
Requires-Dist: Flask
Requires-Dist: Flask-Login
Requires-Dist: simplejson
Dynamic: author
Dynamic: author-email
Dynamic: classifier
Dynamic: description
Dynamic: description-content-type
Dynamic: home-page
Dynamic: keywords
Dynamic: license
Dynamic: platform
Dynamic: requires-dist
Dynamic: summary
